work_hours/__init__.py
work_hours/exception_cn.py
work_hours/work_hours.py
calc_work_hours-0.2024.2.dist-info/LICENSE
calc_work_hours-0.2024.2.dist-info/METADATA
calc_work_hours-0.2024.2.dist-info/WHEEL
calc_work_hours-0.2024.2.dist-info/top_level.txt
calc_work_hours-0.2024.2.dist-info/RECORD
