Metadata-Version: 2.1
Name: calc-work-hours
Version: 0.2024.2
Summary: Given two datetimes, calculate the working hours between them.
Author-email: Yosef HE <h7w8@qq.com>
License: MIT License
Project-URL: Homepage, https://github.com/williamxhero/work_hours
Keywords: work hour,workhour,working hour,workinghour,work day,workday,working day,workingday
Classifier: Programming Language :: Python :: 3
Classifier: License :: OSI Approved :: MIT License
Classifier: Operating System :: OS Independent
Requires-Python: >=3.11
License-File: LICENSE
